command_log/__init__.py
command_log/admin.py
command_log/apps.py
command_log/commands.py
command_log/management/commands/__init__.py
command_log/management/commands/base.py
command_log/management/commands/truncate_management_command_log.py
command_log/migrations/0001_initial.py
command_log/migrations/0002_add_error_to_log.py
command_log/migrations/0003_managementcommandlog_truncate_at.py
command_log/migrations/__init__.py
command_log/models.py
command_log/utils/__init__.py
command_log/utils/signals.py
django_command_log-2.3.0.dist-info/METADATA
django_command_log-2.3.0.dist-info/WHEEL
django_command_log-2.3.0.dist-info/licenses/LICENSE
django_command_log-2.3.0.dist-info/RECORD
